dgisim/__init__.py
dgisim/_env_check.py
dgisim/agents.py
dgisim/card.py
dgisim/char.py
dgisim/effect.py
dgisim/status.py
dgisim/summon.py
dgisim/support.py
dgisim/_core/__init__.py
dgisim/_core/agents.py
dgisim/_core/cli.py
dgisim/_core/deck.py
dgisim/_core/dice.py
dgisim/_core/element.py
dgisim/_core/event.py
dgisim/_core/game_state_machine.py
dgisim/_core/mode.py
dgisim/_core/player_agent.py
dgisim/_core/action/__init__.py
dgisim/_core/action/action.py
dgisim/_core/action/action_generator.py
dgisim/_core/action/action_generator_generator.py
dgisim/_core/action/enums.py
dgisim/_core/action/types.py
dgisim/_core/card/__init__.py
dgisim/_core/card/card.py
dgisim/_core/card/cards.py
dgisim/_core/card/cards_set.py
dgisim/_core/character/__init__.py
dgisim/_core/character/character.py
dgisim/_core/character/characters.py
dgisim/_core/character/characters_set.py
dgisim/_core/character/enums.py
dgisim/_core/effect/__init__.py
dgisim/_core/effect/effect.py
dgisim/_core/effect/effect_stack.py
dgisim/_core/effect/effects_template.py
dgisim/_core/effect/enums.py
dgisim/_core/effect/structs.py
dgisim/_core/encoding/__init__.py
dgisim/_core/encoding/encoding_plan.py
dgisim/_core/encoding/mappings.py
dgisim/_core/env/__init__.py
dgisim/_core/env/linear_env.py
dgisim/_core/helper/__init__.py
dgisim/_core/helper/hashable_dict.py
dgisim/_core/helper/level_print.py
dgisim/_core/helper/quality_of_life.py
dgisim/_core/phase/__init__.py
dgisim/_core/phase/phase.py
dgisim/_core/phase/all_omni/__init__.py
dgisim/_core/phase/all_omni/roll_phase.py
dgisim/_core/phase/default/__init__.py
dgisim/_core/phase/default/action_phase.py
dgisim/_core/phase/default/card_select_phase.py
dgisim/_core/phase/default/end_phase.py
dgisim/_core/phase/default/game_end_phase.py
dgisim/_core/phase/default/roll_phase.py
dgisim/_core/phase/default/starting_hand_select_phase.py
dgisim/_core/state/__init__.py
dgisim/_core/state/enums.py
dgisim/_core/state/game_state.py
dgisim/_core/state/player_state.py
dgisim-0.5.0.dist-info/LICENSE
dgisim-0.5.0.dist-info/METADATA
dgisim-0.5.0.dist-info/WHEEL
dgisim-0.5.0.dist-info/top_level.txt
dgisim-0.5.0.dist-info/RECORD
