Metadata-Version: 2.1
Name: dgisim
Version: 0.5.0
Summary: A highly customizable Genius Invokation TCG Simulator for AI training
Author: Jarvis Yu
License: MIT License
Project-URL: source, https://github.com/Jarvis-Yu/Dottore-Genius-Invokation-TCG-Simulator
Project-URL: tracker, https://github.com/Jarvis-Yu/Dottore-Genius-Invokation-TCG-Simulator/issues
Project-URL: changelog, https://github.com/Jarvis-Yu/Dottore-Genius-Invokation-TCG-Simulator/blob/master/CHANGELOG.md
Project-URL: documentation, https://dottore-genius-invokation-tcg-simulator.readthedocs.io/en/stable/
Classifier: Development Status :: 4 - Beta
Classifier: Intended Audience :: Science/Research
Classifier: Intended Audience :: Developers
Classifier: License :: OSI Approved :: MIT License
Classifier: Programming Language :: Python
Classifier: Programming Language :: Python :: 3
Classifier: Programming Language :: Python :: 3.10
Classifier: Programming Language :: Python :: 3.11
Classifier: Programming Language :: Python :: 3.12
Classifier: Programming Language :: Python :: 3 :: Only
Classifier: Typing :: Typed
Classifier: Operating System :: Microsoft :: Windows
Classifier: Operating System :: POSIX
Classifier: Operating System :: Unix
Classifier: Operating System :: MacOS
Requires-Python: >=3.10
License-File: LICENSE
Requires-Dist: typing-extensions >=4.7.1
